nanocom/__init__.py
nanocom/__main__.py
nanocom-2.0.1.dist-info/LICENSE
nanocom-2.0.1.dist-info/METADATA
nanocom-2.0.1.dist-info/WHEEL
nanocom-2.0.1.dist-info/entry_points.txt
nanocom-2.0.1.dist-info/top_level.txt
nanocom-2.0.1.dist-info/RECORD
