Metadata-Version: 2.1
Name: nanocom
Version: 2.0.1
Summary: Ultra simple command line serial client.
Home-page: https://github.com/rossmacarthur/nanocom
Author: Ross MacArthur
Author-email: ross@macarthur.io
License: UNKNOWN
Download-URL: https://github.com/rossmacarthur/nanocom/archive/2.0.1.tar.gz
Project-URL: Issue Tracker, https://github.com/rossmacarthur/nanocom/issues
Keywords: serial client cli pyserial
Platform: UNKNOWN
Classifier: Development Status :: 4 - Beta
Classifier: Environment :: Console
Classifier: License :: OSI Approved :: MIT License
Classifier: Natural Language :: English
Classifier: Operating System :: POSIX
Classifier: Programming Language :: Python
Classifier: Programming Language :: Python :: 3
Classifier: Programming Language :: Python :: 3.6
Classifier: Programming Language :: Python :: 3.7
Classifier: Programming Language :: Python :: 3.8
Requires-Dist: click (~=7.0)
Requires-Dist: pyserial (~=3.4)
